{"_id": "25f0dd66d818181caf7dbd5b0919b8c9", "_rev": "1-073e398ad6c6024ea155a4459c995aab", "created_at": "Sat May 07 01:06:31 +0000 2022", "id": 1522744652402671600, "id_str": "1522744652402671616", "text": "I have a bag of goodies.\n\nAs it's a cold day might be time to get a little creative .....\n\n#zettaflorencefitzroy\u2026 https://t.co/rObmW9LGQz", "source": "<a href=\"http://instagram.com\" rel=\"nofollow\">Instagram</a>", "truncated": true, "in_reply_to_status_id": null, "in_reply_to_status_id_str": null, "in_reply_to_user_id": null, "in_reply_to_user_id_str": null, "in_reply_to_screen_name": null, "user": {"id": 31628539, "id_str": "31628539", "name": "Patrizia Pollard", "screen_name": "patmar68", "location": "Melbourne, Australia", "url": null, "description": "Life is short so do what you want when you want.  Regrets are a waste of time", "translator_type": "none", "protected": false, "verified": false, "followers_count": 126, "friends_count": 612, "listed_count": 2, "favourites_count": 783, "statuses_count": 1986, "created_at": "Thu Apr 16 03:33:09 +0000 2009", "utc_offset": null, "time_zone": null, "geo_enabled": true, "lang": null, "contributors_enabled": false, "is_translator": false, "profile_background_color": "022330", "profile_background_image_url": "http://abs.twimg.com/images/themes/theme15/bg.png", "profile_background_image_url_https": "https://abs.twimg.com/images/themes/theme15/bg.png", "profile_background_tile": false, "profile_link_color": "0084B4", "profile_sidebar_border_color": "A8C7F7", "profile_sidebar_fill_color": "C0DFEC", "profile_text_color": "333333", "profile_use_background_image": true, "profile_image_url": "http://pbs.twimg.com/profile_images/1441341892684247043/uPIH5bzW_normal.jpg", "profile_image_url_https": "https://pbs.twimg.com/profile_images/1441341892684247043/uPIH5bzW_normal.jpg", "profile_banner_url": "https://pbs.twimg.com/profile_banners/31628539/1414706362", "default_profile": false, "default_profile_image": false, "following": null, "follow_request_sent": null, "notifications": null, "withheld_in_countries": []}, "geo": {"type": "Point", "coordinates": [-37.8023, 144.9793]}, "coordinates": {"type": "Point", "coordinates": [144.9793, -37.8023]}, "place": {"id": "01864a8a64df9dc4", "url": "https://api.twitter.com/1.1/geo/id/01864a8a64df9dc4.json", "place_type": "city", "name": "Melbourne", "full_name": "Melbourne, Victoria", "country_code": "AU", "country": "Australia", "bounding_box": {"type": "Polygon", "coordinates": [[[144.593742, -38.433859], [144.593742, -37.511274], [145.512529, -37.511274], [145.512529, -38.433859]]]}, "attributes": {}}, "contributors": null, "is_quote_status": false, "extended_tweet": {"full_text": "I have a bag of goodies.\n\nAs it's a cold day might be time to get a little creative .....\n\n#zettaflorencefitzroy \n#creative \n#colddaycreativity @ Fitzroy, Victoria https://t.co/BWaj2bU0Cl", "display_text_range": [0, 187], "entities": {"hashtags": [{"text": "zettaflorencefitzroy", "indices": [91, 112]}, {"text": "creative", "indices": [114, 123]}, {"text": "colddaycreativity", "indices": [125, 143]}], "urls": [{"url": "https://t.co/BWaj2bU0Cl", "expanded_url": "https://www.instagram.com/p/CdPN9BdPVgV/?igshid=YTgzYjQ4ZTY=", "display_url": "instagram.com/p/CdPN9BdPVgV/\u2026", "indices": [164, 187]}], "user_mentions": [], "symbols": []}}, "quote_count": 0, "reply_count": 0, "retweet_count": 0, "favorite_count": 0, "entities": {"hashtags": [{"text": "zettaflorencefitzroy", "indices": [91, 112]}], "urls": [{"url": "https://t.co/rObmW9LGQz", "expanded_url": "https://twitter.com/i/web/status/1522744652402671616", "display_url": "twitter.com/i/web/status/1\u2026", "indices": [114, 137]}], "user_mentions": [], "symbols": []}, "favorited": false, "retweeted": false, "possibly_sensitive": false, "filter_level": "low", "lang": "en", "timestamp_ms": "1651885591017"}